_jnpy.cpython-310-x86_64-linux-gnu.so
jnpy/__init__.py
jnpy/bio/__init__.py
jnpy/bio/pdb.py
jnpy-0.1.12.dist-info/LICENSE
jnpy-0.1.12.dist-info/METADATA
jnpy-0.1.12.dist-info/WHEEL
jnpy-0.1.12.dist-info/top_level.txt
jnpy-0.1.12.dist-info/RECORD
