Metadata-Version: 2.1
Name: jnpy
Version: 0.1.12
Summary: Jian's Python Library
Home-page: https://github.com/hust220/jnpy
Author: Jian Wang
Author-email: jianopt@gmail.com
License-File: LICENSE
Provides-Extra: test
Requires-Dist: pytest ; extra == 'test'
